ezm3u8/__init__.py
ezm3u8/channel.py
ezm3u8/episode.py
ezm3u8/m3u8.py
ezm3u8/movie.py
ezm3u8/tvshow.py
ezm3u8-0.1.0.dist-info/METADATA
ezm3u8-0.1.0.dist-info/WHEEL
ezm3u8-0.1.0.dist-info/RECORD
